fieldsets_with_inlines/__init__.py
fieldsets_with_inlines/mixins.py
fieldsets_with_inlines/templates/fieldsets_with_inlines/change_form.html
fieldsets_with_inlines/templates/fieldsets_with_inlines/fieldset.html
django_fieldsets_with_inlines-0.6.dist-info/LICENSE
django_fieldsets_with_inlines-0.6.dist-info/METADATA
django_fieldsets_with_inlines-0.6.dist-info/WHEEL
django_fieldsets_with_inlines-0.6.dist-info/top_level.txt
django_fieldsets_with_inlines-0.6.dist-info/RECORD
