Metadata-Version: 2.1
Name: django-fieldsets-with-inlines
Version: 0.6
Summary: Mixin inlines and fieldsets in Django admin.
Home-page: https://github.com/robertkovac/django-fieldsets-with-inlines
Author: Robert Kovac
Author-email: robert.kovac@gmail.com
License: MIT
Platform: UNKNOWN
Classifier: Programming Language :: Python :: 3
Classifier: License :: OSI Approved :: MIT License
Classifier: Operating System :: OS Independent
Classifier: Framework :: Django
Classifier: Framework :: Django :: 3.0
Classifier: Intended Audience :: Developers
Requires-Python: >=3.4
